{
    "max_thrust": 1816.8482,
    "m_dot_max": 1.038,
    "p_cc_max": 1767425.0519,
    "impulse": 5771.8541,
    "isp": 161.7427,
    "Mox_initial": 3.465,
    "Mox_used": 3.009,
    "Vox_used": 3.8939,
    "Mfuel_initial": 0.6319,
    "Mfuel_used": 0.6319,
    "Vfuel_used": 0.8009,
    "of_ratio": 4.762,
    "avg_mdot_ox": 0.6857,
    "avg_mdot_fuel": 0.1441,
    "start_p_oxtank": 6498711.5775,
    "end_p_oxtank": 2513657.7914,
    "start_p_fueltank": 6207604.5945,
    "end_p_fueltank": 4540946.4727,
    "A_inj_ox_eff": 3.0581e-05,
    "A_inj_fuel_eff": 2.0805e-06,
    "A_inj_o_only": 0.0085,
    "A_inj_f_only": 2.1e-06,
    "exit_mach": 2.935,
    "burn_time": 4.3847,
    "ideal_delta_v": 85.8614,
    "ideal_alt": 375.8762
}